{
  "_id": "5e1459c0de5387793380ac7b",
  "formName": "sd",
  "owner": "jsobiecki01@gmail.com",
  "cooperators": [
    "jsobiecki01@gmail.com",
    "jsobiecki01@gmail.com",
    "jsobiecki01@gmail.com"
  ],
  "inputFields": [
    {
      "name": "Imię",
      "type": "Text",
      "content": "Jan"
    },
    {
      "name": "Nazwisko",
      "type": "Text",
      "content": "Kowalski"
    }
  ],
  "stateFields": [
    {
      "name": "A",
      "assignedTo": "jsobiecki01@gmail.com"
    },
    {
      "name": "B",
      "assignedTo": "jsobiecki01@gmail.com"
    },
    {
      "name": "C",
      "assignedTo": "jsobiecki01@gmail.com"
    }
  ],
  "currentState": {
    "name": "C",
    "assignedTo": "jsobiecki01@gmail.com"
  },
  "history": [
    {
      "prevState": "A",
      "nextState": "B",
      "username": "jsobiecki01@gmail.com",
      "comment": ""
    },
    {
      "prevState": "A",
      "nextState": "C",
      "username": "jsobiecki01@gmail.com",
      "comment": "Wypełniony poprawnie"
    }
  ]
}